{
    "config": [
        {
            "DISPLAY_BUF": 1536000,
            "OFFSET": 561152,
            "FRAMEBUFFER1_ADDR": "0xC0000000",
            "FRAMEBUFFER2_ADDR": "0xC0200000",
            "LVGL_MEMORY_POOL_ADDR": "0xC0400000",
            "LVGL_MEMORY_POOL_SIZE": "2097152",
            "LVGL_MEMORY_END": "0xC0600000",
            "STEERING_ALLOC_ADDR": "0xC0600000",
            "STEERING_ALLOC_SIZE": "2097152",
            "STEERING_ALLOC_END": "0xC0800000",
            "MEMORY_END": "0xC0800000"
        }
    ]
}
